odoo/addons/l10n_ro_account_bank_statement_import_mt940_brd/README.rst
odoo/addons/l10n_ro_account_bank_statement_import_mt940_brd/__init__.py
odoo/addons/l10n_ro_account_bank_statement_import_mt940_brd/__manifest__.py
odoo/addons/l10n_ro_account_bank_statement_import_mt940_brd/data/specificatii_fisiere_ro.pdf
odoo/addons/l10n_ro_account_bank_statement_import_mt940_brd/i18n/l10n_ro_account_bank_statement_import_mt940_brd.pot
odoo/addons/l10n_ro_account_bank_statement_import_mt940_brd/models/__init__.py
odoo/addons/l10n_ro_account_bank_statement_import_mt940_brd/models/account_bank_statement_import.py
odoo/addons/l10n_ro_account_bank_statement_import_mt940_brd/models/account_journal.py
odoo/addons/l10n_ro_account_bank_statement_import_mt940_brd/models/mt940.py
odoo/addons/l10n_ro_account_bank_statement_import_mt940_brd/readme/CONTRIBUTORS.rst
odoo/addons/l10n_ro_account_bank_statement_import_mt940_brd/readme/DESCRIPTION.rst
odoo/addons/l10n_ro_account_bank_statement_import_mt940_brd/static/description/icon.png
odoo/addons/l10n_ro_account_bank_statement_import_mt940_brd/static/description/icon.svg
odoo/addons/l10n_ro_account_bank_statement_import_mt940_brd/static/description/index.html
odoo/addons/l10n_ro_account_bank_statement_import_mt940_brd/test_files/test_brd_940.txt
odoo/addons/l10n_ro_account_bank_statement_import_mt940_brd/tests/__init__.py
odoo/addons/l10n_ro_account_bank_statement_import_mt940_brd/tests/test_import_bank_statement.py
odoo14_addon_l10n_ro_account_bank_statement_import_mt940_brd-14.0.1.4.0.dist-info/METADATA
odoo14_addon_l10n_ro_account_bank_statement_import_mt940_brd-14.0.1.4.0.dist-info/WHEEL
odoo14_addon_l10n_ro_account_bank_statement_import_mt940_brd-14.0.1.4.0.dist-info/top_level.txt
odoo14_addon_l10n_ro_account_bank_statement_import_mt940_brd-14.0.1.4.0.dist-info/RECORD
